FastApi_J2S/core.py
FastApi_J2S/core_server.py
fastapi_j2s-0.1.dist-info/LICENSE
fastapi_j2s-0.1.dist-info/METADATA
fastapi_j2s-0.1.dist-info/WHEEL
fastapi_j2s-0.1.dist-info/top_level.txt
fastapi_j2s-0.1.dist-info/RECORD
