Metadata-Version: 2.2
Name: FastApi_J2S
Version: 0.1
Summary: Fast Api With Dictionary
Home-page: https://github.com/staykimin/MFastApi-J2S
Author: KIMIN
Author-email: staykimin@gmail.com
License: MIT
Project-URL: Documentation, https://github.com/staykimin/FastApi-J2S
Project-URL: Funding, https://github.com/staykimin/FastApi-J2S
Project-URL: Say Thanks!, https://saweria.co/staykimin
Project-URL: Source, https://github.com/staykimin/FastApi-J2S
Project-URL: Tracker, https://github.com/staykimin/FastApi-J2S/issues
Keywords: Kimin,FastApi,FastApi-J2S,J2S
Classifier: Development Status :: 3 - Alpha
Classifier: Intended Audience :: Developers
Classifier: Topic :: Utilities
Classifier: License :: OSI Approved :: MIT License
Classifier: Programming Language :: Python :: 3
Classifier: Programming Language :: Python :: 3.7
Classifier: Programming Language :: Python :: 3.8
Classifier: Programming Language :: Python :: 3.9
Classifier: Programming Language :: Python :: 3.10
License-File: LICENSE
Requires-Dist: Modul-Wrapper
Requires-Dist: Jinja2
Requires-Dist: mysql-connector-python
Requires-Dist: requests
Dynamic: author
Dynamic: author-email
Dynamic: classifier
Dynamic: description
Dynamic: description-content-type
Dynamic: home-page
Dynamic: keywords
Dynamic: license
Dynamic: project-url
Dynamic: requires-dist
Dynamic: summary
